geojsonformer/__init__.py
geojsonformer/geojsonformer.py
geojsonformer-0.1.3.dist-info/LICENSE
geojsonformer-0.1.3.dist-info/METADATA
geojsonformer-0.1.3.dist-info/WHEEL
geojsonformer-0.1.3.dist-info/top_level.txt
geojsonformer-0.1.3.dist-info/RECORD
