Metadata-Version: 2.1
Name: geojsonformer
Version: 0.1.3
Author: Arminas Šidlauskas
Classifier: Operating System :: Microsoft :: Windows :: Windows 10
Classifier: Operating System :: POSIX :: Linux
Classifier: License :: OSI Approved :: MIT License
Requires-Python: >=3.10
License-File: LICENSE
Requires-Dist: numpy
Requires-Dist: shapely
